demetriek/__init__.py
demetriek/cloud.py
demetriek/const.py
demetriek/device.py
demetriek/exceptions.py
demetriek/models.py
demetriek/py.typed
demetriek-1.3.0.dist-info/METADATA
demetriek-1.3.0.dist-info/WHEEL
demetriek-1.3.0.dist-info/RECORD
