Metadata-Version: 2.3
Name: demetriek
Version: 1.3.0
Summary: Asynchronous Python client for LaMetric TIME devices
License: MIT
Keywords: lamtric,api,async,client
Author: Franck Nijhof
Author-email: opensource@frenck.dev
Maintainer: Franck Nijhof
Maintainer-email: opensource@frenck.dev
Requires-Python: >=3.11,<4.0
Classifier: Development Status :: 4 - Beta
Classifier: Framework :: AsyncIO
Classifier: Intended Audience :: Developers
Classifier: License :: OSI Approved :: MIT License
Classifier: Natural Language :: English
Classifier: Programming Language :: Python :: 3
Classifier: Programming Language :: Python :: 3.11
Classifier: Programming Language :: Python :: 3.12
Classifier: Programming Language :: Python :: 3.13
Classifier: Topic :: Software Development :: Libraries :: Python Modules
Requires-Dist: aiohttp (>=3.0.0)
Requires-Dist: awesomeversion (>=21.10.1)
Requires-Dist: backoff (>=2.2.0)
Requires-Dist: mashumaro (>=3.10)
Requires-Dist: orjson (>=3.9.8)
Requires-Dist: yarl (>=1.6.0)
Project-URL: Bug Tracker, https://github.com/frenck/python-demetriek/issues
Project-URL: Changelog, https://github.com/frenck/python-demetriek/releases
Project-URL: Documentation, https://github.com/frenck/python-demetriek
Project-URL: Homepage, https://github.com/frenck/python-demetriek
Project-URL: Repository, https://github.com/frenck/python-demetriek
